shipflowmotionshelpers/__init__.py
shipflowmotionshelpers/_version.py
shipflowmotionshelpers/errors.py
shipflowmotionshelpers/preprocess.py
shipflowmotionshelpers/shipflowmotionshelpers.py
shipflowmotionshelpers/tests/__init__.py
shipflowmotionshelpers/tests/test_shipflowmotionshelpers.py
shipflowmotionshelpers-0.1.11.dist-info/AUTHORS.rst
shipflowmotionshelpers-0.1.11.dist-info/LICENSE
shipflowmotionshelpers-0.1.11.dist-info/METADATA
shipflowmotionshelpers-0.1.11.dist-info/WHEEL
shipflowmotionshelpers-0.1.11.dist-info/top_level.txt
shipflowmotionshelpers-0.1.11.dist-info/RECORD
