Metadata-Version: 2.1
Name: shipflowmotionshelpers
Version: 0.1.11
Summary: Python helper function for ShipFlow Motions
Home-page: https://github.com/martinlarsalbert/shipflowmotionshelpers
Author: Martin Alexandersson
Author-email: maralex@chalmers.se
License: MIT license
Keywords: shipflowmotionshelpers
Platform: UNKNOWN
Classifier: Development Status :: 2 - Pre-Alpha
Classifier: Intended Audience :: Developers
Classifier: License :: OSI Approved :: MIT License
Classifier: Natural Language :: English
Classifier: Programming Language :: Python :: 3
Classifier: Programming Language :: Python :: 3.5
Classifier: Programming Language :: Python :: 3.6
Classifier: Programming Language :: Python :: 3.7
Classifier: Programming Language :: Python :: 3.8
Requires-Python: >=3.5
